iRRBS/__init__.py
iRRBS/irrbs_pipeline.py
iRRBS/run_irrbs.py
iRRBS/suppress.py
iRRBS-1.1.1.dist-info/LICENSE
iRRBS-1.1.1.dist-info/METADATA
iRRBS-1.1.1.dist-info/WHEEL
iRRBS-1.1.1.dist-info/top_level.txt
iRRBS-1.1.1.dist-info/RECORD
