Metadata-Version: 2.1
Name: iRRBS
Version: 1.1.1
Summary: RRBS tool for deleting artificial cytosins
Home-page: https://github.com/fothia/iRRBS
Download-URL: https://github.com/fothia/iRRBS/archive/refs/tags/v1.1.0.tar.gz
Author: Abel Fothi
Author-email: fothi.abel@gmail.com
License: MIT
Classifier: Development Status :: 5 - Production/Stable
Classifier: Intended Audience :: Science/Research
Classifier: Operating System :: Unix
Classifier: License :: OSI Approved :: MIT License
Classifier: Programming Language :: Python :: 3
License-File: LICENSE
Requires-Dist: pysam
Requires-Dist: pybedtools
